pypmc/_version.py
pypmc/__init__.py
pypmc/tools/_linalg.cpython-310-darwin.so
pypmc/tools/_probability_densities.py
pypmc/tools/convergence.py
pypmc/tools/parallel_sampler.py
pypmc/tools/util.py
pypmc/tools/regularize_test.py
pypmc/tools/__init__.py
pypmc/tools/convergence_test.py
pypmc/tools/_doc.py
pypmc/tools/linalg_test.py
pypmc/tools/parallel_sampler_test.py
pypmc/tools/_plot.py
pypmc/tools/_regularize.cpython-310-darwin.so
pypmc/tools/plot_test.py
pypmc/tools/_history.py
pypmc/tools/indicator/indicator_factory_test.py
pypmc/tools/indicator/__init__.py
pypmc/tools/indicator/_indicator_factory.py
pypmc/tools/indicator/_indicator_merge.py
pypmc/mix_adapt/variational_test.py
pypmc/mix_adapt/hierarchical.py
pypmc/mix_adapt/__init__.py
pypmc/mix_adapt/r_value.py
pypmc/mix_adapt/hierarchical_test.py
pypmc/mix_adapt/variational.cpython-310-darwin.so
pypmc/mix_adapt/r_value_test.py
pypmc/mix_adapt/pmc.cpython-310-darwin.so
pypmc/mix_adapt/pmc_test.py
pypmc/density/base_test.py
pypmc/density/partition_test.py
pypmc/density/mixture.cpython-310-darwin.so
pypmc/density/student_t.cpython-310-darwin.so
pypmc/density/__init__.py
pypmc/density/gauss.cpython-310-darwin.so
pypmc/density/_partition.py
pypmc/density/student_t_test.py
pypmc/density/mixture_test.py
pypmc/density/base.py
pypmc/density/gauss_test.py
pypmc/sampler/importance_sampling_test.py
pypmc/sampler/markov_chain_test.py
pypmc/sampler/markov_chain.py
pypmc/sampler/__init__.py
pypmc/sampler/importance_sampling.py
pypmc-1.2.5.dist-info/RECORD
pypmc-1.2.5.dist-info/WHEEL
pypmc-1.2.5.dist-info/top_level.txt
pypmc-1.2.5.dist-info/METADATA
pypmc-1.2.5.dist-info/licenses/LICENSE
