Metadata-Version: 2.4
Name: pypmc
Version: 1.2.5
Summary: A toolkit for adaptive importance sampling featuring implementations of variational Bayes, population Monte Carlo, and Markov chains.
Home-page: https://github.com/pypmc/pypmc
Author: Frederik Beaujean, Stephan Jahn
Author-email: beaujean@mytum.de, stephan.jahn@mytum.de
License: GPLv2
Platform: Unix
Classifier: Development Status :: 5 - Production/Stable
Classifier: Intended Audience :: Developers
Classifier: Intended Audience :: Science/Research
Classifier: License :: OSI Approved :: GNU General Public License v2 or later (GPLv2+)
Classifier: Operating System :: Unix
Classifier: Programming Language :: Cython
Classifier: Programming Language :: Python
Classifier: Programming Language :: Python :: 3
Classifier: Topic :: Scientific/Engineering
Classifier: Topic :: Scientific/Engineering :: Mathematics
Requires-Python: >=3.9
License-File: LICENSE
Requires-Dist: numpy>=1.6
Requires-Dist: scipy
Requires-Dist: setuptools>=40.8.0
Provides-Extra: testing
Requires-Dist: nose; extra == "testing"
Provides-Extra: plotting
Requires-Dist: matplotlib; extra == "plotting"
Provides-Extra: parallelization
Requires-Dist: mpi4py; extra == "parallelization"
Dynamic: author
Dynamic: author-email
Dynamic: classifier
Dynamic: description
Dynamic: home-page
Dynamic: license
Dynamic: license-file
Dynamic: platform
Dynamic: provides-extra
Dynamic: requires-dist
Dynamic: requires-python
Dynamic: summary
